joeutil/__init__.py
joeutil/adptools.py
joeutil-0.0.5.dist-info/LICENSE
joeutil-0.0.5.dist-info/METADATA
joeutil-0.0.5.dist-info/WHEEL
joeutil-0.0.5.dist-info/top_level.txt
joeutil-0.0.5.dist-info/RECORD
