Metadata-Version: 2.1
Name: joeutil
Version: 0.0.5
Summary: ADP Utils
Home-page: https://blog.naver.com/kim_junhan
Author: joe
Author-email: kim_junhan@naver.com
Project-URL: Bug Tracker, https://blog.naver.com/kim_junhan
Classifier: Programming Language :: Python :: 3
Classifier: License :: OSI Approved :: MIT License
Classifier: Operating System :: OS Independent
Requires-Python: >=3.6
License-File: LICENSE
Requires-Dist: imblearn
Requires-Dist: statsmodels
Requires-Dist: xgboost
Requires-Dist: lightgbm
